{
  "id": 814647,
  "original_id": 732695,
  "lesson_id": 143253,
  "user_id": 225,
  "course_id": 81406,
  "type": "video",
  "title": "Movie Cast Example",
  "index": 63,
  "is_hidden": false,
  "lesson_markable_id": null,
  "rubric_id": null,
  "rubric_points": null,
  "auto_points": null,
  "lti_deep_link_id": null,
  "status": "unseen",
  "correct": null,
  "response": null,
  "created_at": "2025-08-10T07:49:33.599745+10:00",
  "updated_at": null,
  "video_url": "https://youtu.be/4HSHs8_x4HQ"
}